pyopath/__init__.py
pyopath/doer.py
pyopath/nodewrappers/__init__.py
pyopath/nodewrappers/base.py
pyopath/nodewrappers/etree.py
pyopath/nodewrappers/registry.py
pyopath/xpath/__init__.py
pyopath/xpath/AST/__init__.py
pyopath/xpath/AST/ast.py
pyopath/xpath/AST/lexer.py
pyopath/xpath/AST/parser.py
PyOPath-0.0.1.dist-info/LICENSE
PyOPath-0.0.1.dist-info/METADATA
PyOPath-0.0.1.dist-info/WHEEL
PyOPath-0.0.1.dist-info/top_level.txt
PyOPath-0.0.1.dist-info/RECORD
